mmfutils-0.7.5.dist-info/METADATA
mmfutils-0.7.5.dist-info/WHEEL
mmfutils-0.7.5.dist-info/entry_points.txt
mmfutils-0.7.5.dist-info/licenses/LICENSE.txt
mmfutils/__init__.py
mmfutils/containers.py
mmfutils/contexts.py
mmfutils/contexts.py.orig
mmfutils/debugging.py
mmfutils/interface.py
mmfutils/math/__init__.py
mmfutils/math/bases/__init__.py
mmfutils/math/bases/bases.py
mmfutils/math/bases/interfaces.py
mmfutils/math/bases/utils.py
mmfutils/math/bessel.py
mmfutils/math/differentiate.py
mmfutils/math/integrate/__init__.py
mmfutils/math/integrate/_ssum_cython.c
mmfutils/math/integrate/_ssum_cython.pyx
mmfutils/math/linalg.py
mmfutils/math/special.py
mmfutils/math/wigner.py
mmfutils/optimize.py
mmfutils/parallel.py
mmfutils/performance/__init__.py
mmfutils/performance/_numexpr_import_check.py
mmfutils/performance/blas.py
mmfutils/performance/fft.py
mmfutils/performance/numexpr.py
mmfutils/performance/threads.py
mmfutils/plot/__init__.py
mmfutils/plot/animation.py
mmfutils/plot/cmaps.py
mmfutils/plot/colors.py
mmfutils/plot/contour.py
mmfutils/plot/errors.py
mmfutils/plot/publish.py
mmfutils/plot/rasterize.py
mmfutils/solve/__init__.py
mmfutils/solve/broyden.py
mmfutils/testing.py
mmfutils-0.7.5.dist-info/RECORD
